dataclassconfig/__init__.py
dataclassconfig/__init__.pyi
dataclassconfig/__version__.py
dataclassconfig/__version__.pyi
dataclassconfig/py.typed
dataclassconfig-0.0.3.dist-info/LICENSE
dataclassconfig-0.0.3.dist-info/METADATA
dataclassconfig-0.0.3.dist-info/WHEEL
dataclassconfig-0.0.3.dist-info/top_level.txt
dataclassconfig-0.0.3.dist-info/RECORD
