Metadata-Version: 2.1
Name: dataclassconfig
Version: 0.0.3
Summary: The simplest interface for working with configuration files
Home-page: https://github.com/rilshok/dataclassconfig
Author: Vladislav A. Proskurov
Author-email: rilshok@pm.me
License: MIT
Classifier: Programming Language :: Python :: 3.6
Classifier: License :: OSI Approved :: MIT License
Classifier: Operating System :: OS Independent
Classifier: Development Status :: 1 - Planning
Requires-Python: >=3.6
License-File: LICENSE
Requires-Dist: dacite
Requires-Dist: pyyaml
